SR3/SR3.py
SR3/__init__.py
SR3/utils.py
SR3/version.py
SR3/math/__init__.py
SR3/math/linalg.py
SR3/math/optimization.py
SR3/math/solvers.py
SR3/math/tensors.py
SR3-0.0.1.1.dist-info/LICENSE.txt
SR3-0.0.1.1.dist-info/METADATA
SR3-0.0.1.1.dist-info/WHEEL
SR3-0.0.1.1.dist-info/top_level.txt
SR3-0.0.1.1.dist-info/RECORD
